Metadata-Version: 2.1
Name: mssql-django
Version: 1.4.2
Summary: Django backend for Microsoft SQL Server
Home-page: https://github.com/microsoft/mssql-django
Author: Microsoft
Author-email: opencode@microsoft.com
License: BSD
Project-URL: Release Notes, https://github.com/microsoft/mssql-django/releases
Keywords: django
Classifier: License :: OSI Approved :: BSD License
Classifier: Framework :: Django
Classifier: Operating System :: POSIX :: Linux
Classifier: Operating System :: Microsoft :: Windows
Classifier: Programming Language :: Python
Classifier: Programming Language :: Python :: 3
Classifier: Programming Language :: Python :: 3.8
Classifier: Programming Language :: Python :: 3.9
Classifier: Programming Language :: Python :: 3.10
Classifier: Programming Language :: Python :: 3.11
Classifier: Programming Language :: Python :: 3.12
Classifier: Framework :: Django :: 3.2
Classifier: Framework :: Django :: 4.0
Classifier: Framework :: Django :: 4.1
Classifier: Framework :: Django :: 4.2
Classifier: Framework :: Django :: 5.0
License-File: LICENSE.txt
License-File: NOTICE.md
Requires-Dist: django<5.1,>=3.2
Requires-Dist: pyodbc>=3.0
Requires-Dist: pytz
